Implementation_BitFusion_v2/Implementation_BitFusion_v2/bitbrick.v
`timescale 1ns / 1ps

// Performs a signed multiplication between two 2-bit inputs.
// - Sign-extends each input to 3 bits if sign_x or sign_y is asserted.
// - Computes signed 6-bit product directly within the module.

module bitbrick(
    input clk,              // Clock signal
    input reset,            // Reset signal
    input [1:0] x,          // 2-bit input operand x
    input [1:0] y,          // 2-bit input operand y
    input sign_x,           // Sign control for x
    input sign_y,           // Sign control for y
    output reg [5:0] p      // 6-bit signed product output
);

    wire signed [2:0] in_x; // Sign-extended version of x
    wire signed [2:0] in_y; // Sign-extended version of y

    // Extend x and y to 3-bit signed values
    assign in_x = {sign_x & x[1], x};   // Sign-extend if sign_x is high and MSB of x is 1
    assign in_y = {sign_y & y[1], y};   // Sign-extend if sign_y is high and MSB of y is 1

    // Check if either x or y is zero and assign p with 0 if true
    always @(*) begin
        if (x == 2'b00 || y == 2'b00) begin
            p = 6'b000000; // Assign 0 to p if either x or y is zero
        end else begin
            p = in_x * in_y; // Perform signed multiplication
        end
    end

endmodule

Implementation_BitFusion_v2/Implementation_BitFusion_v2/tb_bitbrick.v
`timescale 1ns / 1ps

module tb_bitbrick;

    // Declare inputs as regs and outputs as wires
    reg clk;
    reg reset;
    reg [1:0] x;
    reg [1:0] y;
    reg sign_x;
    reg sign_y;
    wire [5:0] p;

    // Instantiate the bitbrick module
    bitbrick uut (
        .clk(clk),
        .reset(reset),
        .x(x),
        .y(y),
        .sign_x(sign_x),
        .sign_y(sign_y),
        .p(p)
    );

    // Generate clock signal
    always begin
        #5 clk = ~clk;  // 100 MHz clock
    end

    // Initialize the test
    initial begin
        // Initialize signals
        clk = 0;
        reset = 0;
        x = 2'b00; // Set to zero
        y = 2'b00; // Set to zero
        sign_x = 0;
        sign_y = 0;

        // Reset the module
        reset = 1;
        #10;
        reset = 0;
        #10;

        // Test case 1: x = 2'b00, y = 2'b00 (Product should be 0)
        x = 2'b00; y = 2'b00;
        #10;

        // Test case 2: x = 2'b01, y = 2'b00 (Product should be 0)
        x = 2'b01; y = 2'b00;
        #10;

        // Test case 3: x = 2'b00, y = 2'b01 (Product should be 0)
        x = 2'b00; y = 2'b01;
        #10;

        // Test case 4: x = 2'b01, y = 2'b01 (Product should be 1)
        x = 2'b01; y = 2'b01;
        #10;

        // Test case 5: x = 2'b10, y = 2'b11 (Product should be -6)
        x = 2'b10; y = 2'b11;
        #10;

        // Test case 6: x = 2'b11, y = 2'b11 (Product should be 6)
        x = 2'b11; y = 2'b11;
        #10;

        // Test case 7: x = 2'b11, y = 2'b10 (Product should be -6)
        x = 2'b11; y = 2'b10;
        #10;

        // Finish simulation
        $finish;
    end

    // Generate the VCD file for GTKWave visualization
    initial begin
        $dumpfile("tb_bitbrick.vcd");  // Specify the VCD file name
        $dumpvars(0, tb_bitbrick);     // Dump all signals
    end

endmodule

Implementation_BitFusion_v2/Implementation_BitFusion_v2/tb_bitbrick.vcd
$date
	Mon May 05 22:38:20 2025
$end
$version
	Icarus Verilog
$end
$timescale
	1ps
$end
$scope module tb_bitbrick $end
$var wire 6 ! p [5:0] $end
$var reg 1 " clk $end
$var reg 1 # reset $end
$var reg 1 $ sign_x $end
$var reg 1 % sign_y $end
$var reg 2 & x [1:0] $end
$var reg 2 ' y [1:0] $end
$scope module uut $end
$var wire 1 " clk $end
$var wire 1 # reset $end
$var wire 1 $ sign_x $end
$var wire 1 % sign_y $end
$var wire 2 ( x [1:0] $end
$var wire 2 ) y [1:0] $end
$var wire 3 * in_y [2:0] $end
$var wire 3 + in_x [2:0] $end
$var reg 6 , p [5:0] $end
$upscope $end
$upscope $end
$enddefinitions $end
#0
$dumpvars
b0 ,
b0 +
b0 *
b0 )
b0 (
b0 '
b0 &
0%
0$
1#
0"
b0 !
$end
#5000
1"
#10000
0"
0#
#15000
1"
#20000
0"
#25000
1"
#30000
0"
b1 +
b1 &
b1 (
#35000
1"
#40000
0"
b1 *
b1 '
b1 )
b0 +
b0 &
b0 (
#45000
1"
#50000
b1 !
b1 ,
0"
b1 +
b1 &
b1 (
#55000
1"
#60000
b110 !
b110 ,
0"
b11 *
b11 '
b11 )
b10 +
b10 &
b10 (
#65000
1"
#70000
b1001 !
b1001 ,
0"
b11 +
b11 &
b11 (
#75000
1"
#80000
b110 !
b110 ,
0"
b10 *
b10 '
b10 )
